soupernova/__about__.py
soupernova/__init__.py
soupernova/blast.py
soupernova-0.1.0.dist-info/METADATA
soupernova-0.1.0.dist-info/WHEEL
soupernova-0.1.0.dist-info/licenses/LICENSE.txt
soupernova-0.1.0.dist-info/RECORD
