Metadata-Version: 2.3
Name: soupernova
Version: 0.1.0
Summary: Make viewing stars a blast
Project-URL: Documentation, https://github.com/Matt Craig/soupernova#readme
Project-URL: Issues, https://github.com/Matt Craig/soupernova/issues
Project-URL: Source, https://github.com/Matt Craig/soupernova
Author-email: Matt Craig <mattwcraig@gmail.com>
License-Expression: MIT
License-File: LICENSE.txt
Classifier: Development Status :: 4 - Beta
Classifier: Programming Language :: Python
Classifier: Programming Language :: Python :: 3.8
Classifier: Programming Language :: Python :: 3.9
Classifier: Programming Language :: Python :: 3.10
Classifier: Programming Language :: Python :: 3.11
Classifier: Programming Language :: Python :: 3.12
Classifier: Programming Language :: Python :: Implementation :: CPython
Classifier: Programming Language :: Python :: Implementation :: PyPy
Requires-Python: >=3.10
Requires-Dist: anywidget
Requires-Dist: astrowidgets
Requires-Dist: ipywidgets
